ig_rest_client/__init__.py
ig_rest_client-0.1.dist-info/LICENSE
ig_rest_client-0.1.dist-info/METADATA
ig_rest_client-0.1.dist-info/WHEEL
ig_rest_client-0.1.dist-info/top_level.txt
ig_rest_client-0.1.dist-info/RECORD
