Metadata-Version: 2.1
Name: ig-rest-client
Version: 0.1
Summary: IG REST trading API client
Home-page: https://github.com/wjszlachta/ig-rest-client
Author: Wojciech Szlachta
Author-email: wojciech@szlachta.net
License: UNKNOWN
Project-URL: Bug Reports, https://github.com/wjszlachta/ig-rest-client/issues
Project-URL: Source, https://github.com/wjszlachta/ig-rest-client
Keywords: IG trading
Platform: UNKNOWN
Classifier: Development Status :: 3 - Alpha
Classifier: Intended Audience :: Developers
Classifier: Topic :: Office/Business :: Financial
Classifier: License :: OSI Approved :: ISC License (ISCL)
Classifier: Programming Language :: Python :: 3
Requires-Dist: requests
